<?xml version="1.0" encoding="utf-8"?>
<SoundBanksInfo Platform="Windows" BasePlatform="Windows" SchemaVersion="16" SoundBankVersion="172">
	<SoundBanks>
		<SoundBank Id="945135624" Type="Event" GUID="{47B3F079-BA98-469C-AA64-962EBC254F0D}" Language="SFX" Hash="{94389D47-562D-23FA-3BC2-8429D0751CB0}">
			<ObjectPath>Item_Crash</ObjectPath>
			<ShortName>Item_Crash</ShortName>
			<Path>Event/Item_Crash.bnk</Path>
			<Media>
				<File Id="52878928" Language="SFX" Streaming="false" Location="Loose">
					<ShortName>Gym Barbell Heavy Drop 3.wav</ShortName>
					<Path>Media/52878928.wem</Path>
					<CachePath>8E/{8ED7C333-1246-08E7-CA84-96BFE1526905}.wem</CachePath>
				</File>
				<File Id="203619646" Language="SFX" Streaming="false" Location="Loose">
					<ShortName>Broken Plastic Drop 1.wav</ShortName>
					<Path>Media/203619646.wem</Path>
					<CachePath>7F/{7FDB10EA-C4BD-1C6E-73F5-F15033FF3E8C}.wem</CachePath>
				</File>
				<File Id="515382230" Language="SFX" Streaming="false" Location="Loose">
					<ShortName>ESM_GB_fx_foley_one_shot_metlimpt_can_several_drop_02_metal_bounce_fall.wav</ShortName>
					<Path>Media/515382230.wem</Path>
					<CachePath>A2/{A22BD5E2-11E5-C207-35F5-0E33A33E4CEC}.wem</CachePath>
				</File>
				<File Id="567395332" Language="SFX" Streaming="false" Location="Loose">
					<ShortName>ESM_GB_fx_foley_one_shot_woodcrsh_smash_box_wood_02_impact_destroy_scatter.wav</ShortName>
					<Path>Media/567395332.wem</Path>
					<CachePath>8F/{8F20A5AA-CC45-98FF-21D7-FCD23932F4F4}.wem</CachePath>
				</File>
				<File Id="950344998" Language="SFX" Streaming="false" Location="Loose">
					<ShortName>ESM_GB_fx_foley_one_shot_woodimpt_smash_door_01_impact_broke_invade.wav</ShortName>
					<Path>Media/950344998.wem</Path>
					<CachePath>05/{052F62F2-22A6-935A-1FD8-22E225926823}.wem</CachePath>
				</File>
				<File Id="979411635" Language="SFX" Streaming="false" Location="Loose">
					<ShortName>ESM_GB_fx_foley_one_shot_woodcrsh_wood_single_big_stick_drop_01_stick_fall_impact.wav</ShortName>
					<Path>Media/979411635.wem</Path>
					<CachePath>8B/{8BB903A2-141D-EBF2-CF79-B8F46F7DAB32}.wem</CachePath>
				</File>
				<File Id="991405809" Language="SFX" Streaming="false" Location="Loose">
					<ShortName>Cloths, Bags, Fabrics, Drop 3.wav</ShortName>
					<Path>Media/991405809.wem</Path>
					<CachePath>66/{66E914B6-9646-C4FA-0992-34AB0AEC2C40}.wem</CachePath>
				</File>
			</Media>
			<Events>
				<Event Id="945135624" Name="Item_Crash" ObjectPath="\Events\Default Work Unit\Item_Crash" GUID="{47B3F079-BA98-469C-AA64-962EBC254F0D}" DurationType="OneShot" DurationMin="0.58146" DurationMax="1.5219687">
					<MediaRefs>
						<MediaRef Id="52878928"/>
						<MediaRef Id="203619646"/>
						<MediaRef Id="515382230"/>
						<MediaRef Id="567395332"/>
						<MediaRef Id="950344998"/>
						<MediaRef Id="979411635"/>
						<MediaRef Id="991405809"/>
					</MediaRefs>
				</Event>
			</Events>
		</SoundBank>
	</SoundBanks>
	<FileHash>{CE72CDB0-73A1-1861-2A93-07F294D4AA90}</FileHash>
</SoundBanksInfo>
